EE324/Module_1/Module_1.srcs/sources_1/new/Bounce_Counter_FSM.v
`timescale 1ns / 1ps
//////////////////////////////////////////////////////////////////////////////////
// Company: 
// Engineer: 
// 
// Create Date: 02/25/2019 03:40:00 PM
// Design Name: 
// Module Name: Bounce_Counter_FSM
// Project Name: 
// Target Devices: 
// Tool Versions: 
// Description: 
// 
// Dependencies: 
// 
// Revision:
// Revision 0.01 - File Created
// Additional Comments:
// 
//////////////////////////////////////////////////////////////////////////////////


module Bounce_Counter_FSM(

    input i_100MHZCLK,
    input i_RST,
    input i_Signal,
    output [13:0] o_DATA,
    output o_CEN
    );
    
    localparam s_WAIT = 2'd0;
    localparam s_ASSERT = 2'd1;
    localparam s_DONE = 2'd2;
  

    wire w_100MHZCLK;
    wire w_RST;
    wire w_Signal;
    reg r_CEN = 1'd0;
    reg [1:0] r_NEXT_STATE = 2'd0;
    reg [1:0] r_CURRENT_STATE = 2'd0;
    reg [13:0] r_COUNTER = 14'd0;
   

   assign w_100MHZCLK = i_100MHZCLK;
   assign w_RST = i_RST;
   assign w_Signal = i_Signal;
   assign o_CEN = r_CEN;
   assign o_DATA = r_COUNTER;
   always@(*)
   begin
        case(r_CURRENT_STATE)
            s_WAIT:
                begin
                    if(i_Signal == 1'd1) 
                        r_NEXT_STATE = s_ASSERT;
                    else 
                    begin
                        r_NEXT_STATE = s_WAIT;
                    end
                end
            s_ASSERT:
                begin
                    if(i_Signal == 1'd0) begin
                        r_NEXT_STATE = s_DONE;
                        end
                    else
                        begin
                        r_NEXT_STATE = s_ASSERT;
                        end
                end
             s_DONE:
                begin
                    r_NEXT_STATE = s_DONE;
                end
              default: 
              r_NEXT_STATE = s_WAIT;
             endcase 
   end
    
   always@(posedge w_100MHZCLK or posedge w_RST)
   begin
        if(w_RST == 1'd1)
            r_CURRENT_STATE <= s_WAIT;
        else
            r_CURRENT_STATE <= r_NEXT_STATE;
   end
   
   
   always@(posedge w_100MHZCLK)
   begin
   if(r_CURRENT_STATE == s_WAIT)
   begin
        r_COUNTER <= 14'd0;
        r_CEN <= 1'd0;
   end
   else if((i_Signal == 1'd1) && (r_CURRENT_STATE != s_DONE)) begin
        r_COUNTER <= r_COUNTER + 1'b1;
        r_CEN <= 1'd1;
        end
   else
        begin
        r_COUNTER <= r_COUNTER;
        r_CEN <= 1'd0;
        end
   end
   
   
endmodule

EE324/Module_1/sim/Bounce_Counter_FSM/obj_dir/trace.vcd
$version Generated by VerilatedVcd $end
$date Wed Aug 28 22:38:23 2019
 $end
$timescale   1ns $end

 $scope module TOP $end
  $var wire  1 ' i_100MHZCLK $end
  $var wire  1 ( i_RST $end
  $var wire  1 ) i_Signal $end
  $var wire  1 + o_CEN $end
  $var wire 14 * o_DATA [13:0] $end
  $scope module Bounce_Counter_FSM $end
   $var wire  1 ' i_100MHZCLK $end
   $var wire  1 ( i_RST $end
   $var wire  1 ) i_Signal $end
   $var wire  1 + o_CEN $end
   $var wire 14 * o_DATA [13:0] $end
   $var wire  1 # r_CEN $end
   $var wire 14 % r_COUNTER [13:0] $end
   $var wire  2 $ r_CURRENT_STATE [1:0] $end
   $var wire  2 & r_NEXT_STATE [1:0] $end
   $var wire  2 - s_ASSERT [1:0] $end
   $var wire  2 . s_DONE [1:0] $end
   $var wire  2 , s_WAIT [1:0] $end
   $var wire  1 ' w_100MHZCLK $end
   $var wire  1 ( w_RST $end
   $var wire  1 ) w_Signal $end
  $upscope $end
 $upscope $end
$enddefinitions $end


#10
0#
b00 $
b00000000000000 %
b00 &
0'
0(
0)
b00000000000000 *
0+
b00 ,
b01 -
b11 .
#15
1'
#20
0'
#25
1'
#30
0'
#35
1'
#40
0'
#45
1'
#50
0'
#55
1'
#60
0'
#65
1'
#70
0'
#75
1'
#80
0'
#85
1'
#90
0'
#95
1'
#100
0'
#105
1'
#110
0'
#115
1'
#120
0'
#125
1'
#130
0'
#135
1'
#140
0'
#145
1'
#150
0'
#155
1'
#160
0'
#165
1'
#170
0'
#175
1'
#180
0'
#185
1'
#190
0'
#195
1'
#200
0'
#205
1'
#210
b01 &
0'
1)
#215
1#
b01 $
b00000000000001 %
1'
b00000000000001 *
1+
#220
0'
#225
b00000000000010 %
1'
b00000000000010 *
#230
0'
#235
b00000000000011 %
1'
b00000000000011 *
#240
0'
#245
b00000000000100 %
1'
b00000000000100 *
#250
0'
#255
b00000000000101 %
1'
b00000000000101 *
#260
0'
#265
b00000000000110 %
1'
b00000000000110 *
#270
0'
#275
b00000000000111 %
1'
b00000000000111 *
#280
0'
#285
b00000000001000 %
1'
b00000000001000 *
#290
0'
#295
b00000000001001 %
1'
b00000000001001 *
#300
0'
#305
b00000000001010 %
1'
b00000000001010 *
#310
b11 &
0'
0)
#315
0#
b11 $
1'
0+
#320
0'
#325
1'
#330
0'
#335
1'
#340
0'
#345
1'
#350
0'
#355
1'
#360
0'
#365
1'
#370
0'
#375
1'
#380
0'
#385
1'
#390
0'
#395
1'
#400
0'
#405
1'
#410
0'
#415
1'
#420
0'
#425
1'
#430
0'
#435
1'
#440
0'
#445
1'
#450
0'
#455
1'
#460
0'
#465
1'
#470
0'
#475
1'
#480
0'
#485
1'
#490
0'
#495
1'
#500
0'
#505
1'
#510
0'
1)
